[{"puzzle": [["E", "N", "A", "G"], ["O", "N", "R", "A"], ["B", "A", "A", "N"]], "solution": ["banana", "orange"]}, {"puzzle": [["E", "N", "G", "M"], ["O", "I", "I", "M"], ["F", "L", "L", "E"]], "solution": ["lemon", "fig", "lime"]}, {"puzzle": [["M", "P", "I", "U"], ["A", "W", "E", "R"], ["I", "L", "P", "K"]], "solution": ["pear", "plum", "kiwi"]}, {"puzzle": [["A", "T", "E", "P"], ["P", "U", "C", "L"], ["N", "O", "C", "O"]], "solution": ["coconut", "apple"]}, {"puzzle": [["P", "T", "C", "E"], ["I", "O", "A", "H"], ["R", "C", "A", "P"]], "solution": ["apricot", "peach"]}]