[{"puzzle": [["S", "A", "P", "O", "N", "E", "O"], ["Y", "B", "R", "A", "T", "N", "T"], ["R", "I", "E", "T", "I", "G", "E"], ["R", "S", "S", "P", "R", "P", "R"], ["K", "I", "R", "A", "R", "C", "E"], ["L", "X", "C", "O", "A", "T", "N"], ["Y", "A", "T", "N", "C", "O", "I"]], "solution": ["taxi", "library", "concrete", "skyscraper", "transportation", "pigeon"]}, {"puzzle": [["O", "L", "E", "U", "S", "T", "S"], ["P", "E", "E", "R", "K", "N", "A"], ["A", "C", "S", "D", "R", "A", "R"], ["R", "H", "T", "A", "A", "U", "T"], ["I", "C", "O", "N", "M", "E", "S"], ["E", "T", "A", "R", "D", "T", "E"], ["P", "L", "S", "T", "A", "R", "U"]], "solution": ["roads", "architecture", "people", "restaurant", "statues", "landmarks"]}, {"puzzle": [["T", "A", "T", "G", "T", "E", "S"], ["O", "R", "H", "L", "R", "U", "Y"], ["P", "E", "I", "E", "I", "O", "H"], ["E", "U", "N", "M", "N", "A", "R"], ["N", "O", "E", "A", "O", "O", "T"], ["M", "S", "R", "A", "T", "N", "F"], ["M", "T", "F", "C", "Y", "O", "U"]], "solution": ["house", "factory", "fountain", "streetlight", "opera", "monument", "mayor"]}, {"puzzle": [["C", "R", "O", "E", "I", "K", "A"], ["S", "N", "G", "N", "A", "L", "M"], ["T", "I", "C", "L", "E", "B", "E"], ["R", "S", "R", "T", "L", "P", "N"], ["A", "O", "S", "W", "S", "A", "I"], ["I", "D", "W", "D", "H", "P", "U"], ["N", "K", "Y", "I", "A", "S", "C"]], "solution": ["train", "asphalt", "sidewalk", "pub", "cinema", "skyline", "crossing", "crowd"]}, {"puzzle": [["J", "O", "B", "T", "U", "T", "Y"], ["B", "S", "N", "N", "C", "T", "N"], ["I", "N", "I", "O", "I", "P", "O"], ["I", "G", "G", "A", "S", "O", "I"], ["D", "L", "I", "S", "E", "R", "U"], ["I", "U", "T", "I", "V", "B", "L"], ["G", "N", "H", "D", "T", "L", "L"]], "solution": ["diversity", "station", "nightclub", "pollution", "building", "sign", "job"]}]