[{"puzzle": [["T", "S", "Y", "U", "A", "O", "S"], ["S", "K", "A", "L", "K", "R", "W"], ["T", "E", "O", "E", "O", "M", "E"], ["A", "X", "N", "S", "H", "L", "E"], ["M", "S", "O", "O", "S", "L", "R"], ["E", "S", "T", "S", "B", "R", "U"], ["E", "B", "A", "L", "C", "L", "Y"]], "solution": ["homework", "classmate", "lesson", "essay", "textbook", "ruler", "syllabus"]}, {"puzzle": [["G", "A", "G", "N", "N", "E", "S"], ["T", "D", "I", "I", "L", "C", "E"], ["R", "N", "G", "N", "E", "E", "R"], ["E", "A", "R", "A", "E", "C", "U"], ["M", "N", "L", "E", "S", "E", "T"], ["U", "R", "A", "D", "A", "S", "C"], ["T", "E", "G", "M", "A", "X", "I"]], "solution": ["learning", "assignment", "grade", "exam", "graduate", "lecture", "science"]}, {"puzzle": [["N", "I", "E", "U", "G", "U", "R"], ["Z", "U", "S", "M", "E", "Y", "O"], ["O", "Y", "P", "E", "O", "L", "S"], ["R", "L", "R", "S", "B", "S", "Y"], ["A", "I", "G", "R", "O", "F", "E"], ["R", "B", "A", "E", "P", "O", "D"], ["Q", "T", "C", "I", "D", "S", "T"]], "solution": ["library", "quiz", "professor", "degree", "biology", "campus", "notes", "study"]}, {"puzzle": [["E", "S", "C", "E", "E", "E", "T"], ["L", "C", "T", "S", "H", "I", "Y"], ["U", "I", "E", "R", "A", "T", "S"], ["Y", "S", "S", "I", "L", "E", "R"], ["H", "E", "T", "C", "I", "I", "V"], ["D", "P", "H", "X", "N", "U", "P"], ["S", "C", "R", "E", "E", "P", "U"]], "solution": ["university", "pupil", "physics", "schedule", "test", "teacher", "exercise"]}, {"puzzle": [["C", "R", "S", "Y", "R", "T", "D"], ["O", "E", "S", "T", "C", "N", "T"], ["Y", "M", "S", "A", "C", "E", "C"], ["R", "P", "I", "M", "L", "E", "B"], ["T", "A", "P", "E", "O", "U", "J"], ["I", "M", "E", "U", "H", "T", "S"], ["U", "R", "R", "S", "C", "U", "S"]], "solution": ["chemistry", "class", "course", "subject", "student", "primary", "computer"]}]